README.rst
setup.cfg
setup.py
fingym/__init__.py
fingym/fingym.py
fingym/logger.py
fingym.egg-info/PKG-INFO
fingym.egg-info/SOURCES.txt
fingym.egg-info/dependency_links.txt
fingym.egg-info/requires.txt
fingym.egg-info/top_level.txt
fingym/data/SPY_bb_20.csv
fingym/data/SPY_cci.csv
fingym/data/SPY_daily.csv
fingym/data/SPY_obv.csv
fingym/data/SPY_rsi.csv
fingym/data/SPY_sma_200.csv
fingym/data/SPY_sma_50.csv
fingym/data/SPY_sma_9.csv
fingym/data/filtered_aapl_data_10_yrs.csv
fingym/data/filtered_abbv_data_10_yrs.csv
fingym/data/filtered_amd_data_10_yrs.csv
fingym/data/filtered_amzn_data_10_yrs.csv
fingym/data/filtered_amzn_full_weekly.csv
fingym/data/filtered_ba_data_10_yrs.csv
fingym/data/filtered_cgc_data.csv
fingym/data/filtered_cron_data.csv
fingym/data/filtered_googl_data_10_yrs.csv
fingym/data/filtered_spy_2017_2019_all.csv
fingym/data/filtered_spy_data_10_yrs.csv
fingym/data/filtered_tsla_data_10_yrs.csv
fingym/data/iex_SPY_daily.csv
fingym/data/parser.py
fingym/envs/__init__.py
fingym/envs/aapl_envs.py
fingym/envs/abbv_envs.py
fingym/envs/alphavantage_envs.py
fingym/envs/amd_envs.py
fingym/envs/amzn_envs.py
fingym/envs/ba_envs.py
fingym/envs/cgc_envs.py
fingym/envs/cron_envs.py
fingym/envs/env.py
fingym/envs/googl_envs.py
fingym/envs/iex_cloud_envs.py
fingym/envs/spy_envs.py
fingym/envs/tsla_envs.py
fingym/examples/agents/buy_and_hold_agent.py
fingym/examples/agents/deep_evolution.py
fingym/examples/agents/dqn_agent.py
fingym/examples/agents/evolutionary_agent.py
fingym/examples/agents/evolutionary_agent_w_crossover.py
fingym/examples/agents/multi_env_evo_agent.py
fingym/examples/agents/multi_env_evo_agent_tester.py
fingym/examples/agents/random_agent.py
fingym/examples/environments/alphavantage_random_walk_env.py
fingym/examples/environments/random_walk.py
fingym/examples/environments/using_alphavantage_env.py
fingym/examples/environments/using_iex_cloud_env.py
fingym/spaces/__init__.py
fingym/spaces/space.py
tests/aapl_envs_test.py
tests/abbv_envs_test.py
tests/amd_envs_test.py
tests/amzn_envs_test.py
tests/ba_envs_test.py
tests/cgc_envs_test.py
tests/cron_envs_test.py
tests/googl_envs_test.py
