Metadata-Version: 1.1
Name: fingym
Version: 1.0
Summary: A tool for developing reinforcement learning algorithms focused in stock prediction
Home-page: https://github.com/entrpn/fingym/
Author: Juan Acevedo
Author-email: entrpn@gmail.com
License: apache-2.0
Download-URL: https://github.com/entrpn/fingym/archive/v1.0.tar.gz
Keywords: stock-market,stock-price-prediction,python,reinforcement-learning-environments,reinforcement-learning,reinforcement-learning-agents,artificial-intelligence,q-learning,evolution-strategies
Platform: UNKNOWN
Classifier: Development Status :: 4 - Beta
Classifier: Intended Audience :: Developers
Classifier: Topic :: Software Development :: Build Tools
Classifier: License :: OSI Approved :: Apache Software License
Classifier: Programming Language :: Python :: 3.5
Classifier: Programming Language :: Python :: 3.6
Classifier: Programming Language :: Python :: 3.7
